{
  "main": {
    "id": "5324373015726ba8",
    "type": "split",
    "children": [
      {
        "id": "fe00383997785384",
        "type": "tabs",
        "children": [
          {
            "id": "18504473639fff96",
        "id": "4509724f8bf84da7",
        "type": "tabs",
        "children": [
          {
            "id": "e7a7b303c61786dc",
            "type": "leaf",
            "state": {
              "type": "markdown",
              "state": {
                "file": "content/dnd/Strixhaven A Curriculum of Chaos/Factions and Groups/Quandrix College.md",
                "mode": "preview",
                "source": true
              },
              "icon": "lucide-file",
              "title": "Quandrix College"
                "file": "ttrpgs/Campaigns/Strixhaven/Strixhaven.md",
                "mode": "source",
                "source": false
              },
              "icon": "lucide-file",
              "title": "Strixhaven"
            }
          }
        ]
      }
    ],
    "direction": "vertical"
  },
  "left": {
    "id": "ed014269d0d3bc75",
    "type": "mobile-drawer",
    "children": [
      {
        "id": "9c0fa7933756c59e",
        "type": "leaf",
        "state": {
          "type": "file-explorer",
          "state": {
            "sortOrder": "alphabetical",
            "autoReveal": false
          },
          "icon": "lucide-folder-closed",
          "title": "Files"
        }
      },
      {
        "id": "85914c84a58e699c",
        "type": "leaf",
        "state": {
          "type": "search",
          "state": {
            "query": "Quandrix",
            "matchingCase": true,
            "query": "",
            "matchingCase": false,
            "explainSearch": false,
            "collapseAll": false,
            "extraContext": false,
            "sortOrder": "byModifiedTime"
          },
          "icon": "lucide-search",
          "title": "Search"
        }
      },
      {
        "id": "144d85f01ff4da69",
        "type": "leaf",
        "state": {
          "type": "tag",
          "state": {
            "sortOrder": "frequency",
            "useHierarchy": true,
            "showSearch": false,
            "searchQuery": ""
          },
          "icon": "lucide-tags",
          "title": "Tags"
        }
      },
      {
        "id": "381459234c51056f",
        "type": "leaf",
        "state": {
          "type": "all-properties",
          "state": {
            "sortOrder": "frequency",
            "showSearch": false,
            "searchQuery": ""
          },
          "icon": "lucide-archive",
          "title": "All properties"
        }
      },
      {
        "id": "6b17d1cbe2f5d36f",
        "type": "leaf",
        "state": {
          "type": "bookmarks",
          "state": {},
          "icon": "lucide-bookmark",
          "title": "Bookmarks"
        }
      }
    ],
    "currentTab": 0
  },
  "right": {
    "id": "2450fd290c373473",
    "type": "mobile-drawer",
    "children": [
      {
        "id": "35be7e8b8923e000",
        "type": "leaf",
        "state": {
          "type": "backlink",
          "state": {
            "collapseAll": false,
            "extraContext": false,
            "sortOrder": "alphabetical",
            "showSearch": false,
            "searchQuery": "",
            "backlinkCollapsed": false,
            "unlinkedCollapsed": true
          },
          "icon": "links-coming-in",
          "title": "Backlinks"
        }
      },
      {
        "id": "14be79287126c2d9",
        "type": "leaf",
        "state": {
          "type": "outgoing-link",
          "state": {
            "linksCollapsed": false,
            "unlinkedCollapsed": true
          },
          "icon": "links-going-out",
          "title": "Outgoing links"
        }
      },
      {
        "id": "f362dc630ccd9b39",
        "type": "leaf",
        "state": {
          "type": "outline",
          "state": {
            "followCursor": false,
            "showSearch": false,
            "searchQuery": ""
          },
          "icon": "lucide-list",
          "title": "Outline"
        }
      },
      {
        "id": "1d064c730669c614",
        "type": "leaf",
        "state": {
          "type": "initiative-tracker-view",
          "state": {},
          "icon": "initiative-tracker",
          "title": "Initiative Tracker"
        }
      },
      {
        "id": "f1d4c5537ad1196e",
        "type": "leaf",
        "state": {
          "type": "DICE_ROLLER_VIEW",
          "state": {},
          "icon": "dices",
          "title": "Dice Tray"
        }
      }
    ],
    "currentTab": 0,
    "pinned": true
  },
  "right": {
    "id": "b52e9479f5f1490a",
    "type": "mobile-drawer",
    "children": [
      {
        "id": "014330f93ab7ccd9",
        "type": "leaf",
        "state": {
          "type": "backlink",
          "state": {
            "file": "content/dnd/Strixhaven A Curriculum of Chaos/Factions and Groups/Quandrix.md",
            "collapseAll": false,
            "extraContext": false,
            "sortOrder": "alphabetical",
            "showSearch": false,
            "searchQuery": "",
            "backlinkCollapsed": false,
            "unlinkedCollapsed": true
          },
          "icon": "links-coming-in",
          "title": "Backlinks"
        }
      },
      {
        "id": "496724b3fc72c86a",
        "type": "leaf",
        "state": {
          "type": "outgoing-link",
          "state": {
            "file": "ttrpgs/Non Player Characters/Mavinder Sharpbeak.md",
            "linksCollapsed": false,
            "unlinkedCollapsed": true
          },
          "icon": "links-going-out",
          "title": "Outgoing links"
        }
      },
      {
        "id": "23d419aa5609f966",
        "type": "leaf",
        "state": {
          "type": "outline",
          "state": {
            "file": "ttrpgs/Non Player Characters/Mavinder Sharpbeak.md",
            "followCursor": false,
            "showSearch": false,
            "searchQuery": ""
          },
          "icon": "lucide-list",
          "title": "Outline"
        }
      },
      {
        "id": "d413445d97cf1e02",
        "type": "leaf",
        "state": {
          "type": "initiative-tracker-view",
          "state": {},
          "icon": "initiative-tracker",
          "title": "Initiative Tracker"
        }
      },
      {
        "id": "5be1e71c2c0dd685",
        "type": "leaf",
        "state": {
          "type": "DICE_ROLLER_VIEW",
          "state": {},
          "icon": "dices",
          "title": "Dice Tray"
        }
      },
      {
        "id": "5df63e4be13663d8",
        "type": "leaf",
        "state": {
          "type": "initiative-tracker-creature-view",
          "state": {},
          "icon": "initiative-tracker-creature-view",
          "title": "Combatant"
        }
      }
    ],
    "currentTab": 5
    "currentTab": 0
  },
  "left-ribbon": {
    "hiddenItems": {
      "switcher:Open quick switcher": false,
      "graph:Open graph view": false,
      "canvas:Create new canvas": false,
      "daily-notes:Open today's daily note": false,
      "command-palette:Open command palette": false,
      "workspaces:Manage workspace layouts": false,
      "templater-obsidian:Templater": false,
      "obsidian-custom-frames:Open Elvis Parsley - DND Beyond": false,
      "obsidian-5e-statblocks:Open Creature pane": false,
      "initiative-tracker:Initiative Tracker Encounter Builder": false,
      "obsidian-excalidraw-plugin:New drawing": false,
      "obsidian42-brat:BRAT": false,
      "table-editor-obsidian:Advanced Tables Toolbar": false,
      "obsidian-kanban:Create new board": false,
      "helpmate:HelpMate": false,
      "solo-rpg-toolkit:Solo RPG Toolkit": false,
      "obsidian-leaflet-plugin:Open Leaflet Map": false,
      "dbfolder:Create a new database table": false,
      "obsidian-textgenerator-plugin:Generate Text!": false,
      "obsidian-textgenerator-plugin:Text Generator: Templates Packages Manager": false,
      "publish:Publish changes...": false
    }
  },
  "active": "18504473639fff96",
  "lastOpenFiles": [
    "3-Mechanics/CLI/books/strixhaven-a-curriculum-of-chaos/02-life-at-strixhaven.md",
    "content/dnd/Strixhaven A Curriculum of Chaos/Factions and Groups/Quandrix College.md",
    "ttrpgs/ttrpgs.md",
    "z_templates/Update published files.md",
    "content/dnd/Strixhaven A Curriculum of Chaos/Factions and Groups/Quandrix Faculty.md",
    "content/dnd/Strixhaven A Curriculum of Chaos/Factions and Groups/Quandrix Students.md",
    "content/dnd/Strixhaven A Curriculum of Chaos/Non Player Characters/Drazhomir Yarnask.md",
    "2025-05-26.md",
    "ttrpgs/Campaigns/Strixhaven/Strixhaven.md",
    "content/dnd/Strixhaven A Curriculum of Chaos/Non Player Characters/Rosimyffenbip Wuzzfedlims.md",
    "content/dnd/Strixhaven A Curriculum of Chaos/Non Player Characters/Non Player Characters.md",
    "z_templates/Untitled.md",
    "ttrpgs/Untitled 2.md",
    "content/dnd/Strixhaven A Curriculum of Chaos/Non Player Characters/Professor Ruxa.md",
    "content/dnd/Strixhaven A Curriculum of Chaos/Player Characters/Player Characters.md",
    "content/dnd/Strixhaven A Curriculum of Chaos/Factions and Groups",
    "Untitled 1",
    "Untitled",
    "content/dnd/Strixhaven A Curriculum of Chaos/Player Characters/Dalaila Eversnow.md",
    "content/dnd/Strixhaven A Curriculum of Chaos/Player Characters/Borun Erutan.md",
    "content/dnd/Strixhaven A Curriculum of Chaos/Player Characters/Roleck Nevari.md",
    "content/dnd/Strixhaven A Curriculum of Chaos/Player Characters/Zolon Orielson.md",
    "content/dnd/Strixhaven A Curriculum of Chaos/Player Characters/Omari Elderon.md",
    "content/dnd/Strixhaven A Curriculum of Chaos/Player Characters/Elvis Parsley.md",
    "content/dnd/Strixhaven A Curriculum of Chaos/Player Characters/Borun Erutan.png",
    "content/dnd/Strixhaven A Curriculum of Chaos/Player Characters/` = this.employer `.md",
    "3-Mechanics/CLI/classes/wizard-xphb.md",
    "3-Mechanics/CLI/books/players-handbook-2024/08-chapter-7-spells.md",
    "3-Mechanics/CLI/books/players-handbook-2024/04-chapter-3-character-classes.md",
    "ttrpgs/Campaigns/Strixhaven/002_20250525.md",
    "content/dnd/Strixhaven A Curriculum of Chaos/Non Player Characters/Serafina Onyx.jpeg",
    "content/dnd/Strixhaven A Curriculum of Chaos/Non Player Characters/Hofri Ghostforge.jpg",
    "content/dnd/Strixhaven A Curriculum of Chaos/Non Player Characters/Drazhomir Yarnask.webp",
    "content/dnd/Strixhaven A Curriculum of Chaos/Non Player Characters/Professor Mavinda Sharpbeak.png",
    "content/dnd/Strixhaven A Curriculum of Chaos/Non Player Characters/Professor Ruxxa.jpeg",
    "content/dnd/Strixhaven A Curriculum of Chaos/Non Player Characters/IMG_0039.jpeg",
    "content/dnd/Strixhaven A Curriculum of Chaos/Player Characters/Zolon Orielson.png",
    "content/dnd/Strixhaven A Curriculum of Chaos/Non Player Characters/Urzmaktok Grojsh.png",
    "content/dnd/Strixhaven A Curriculum of Chaos/Non Player Characters/Urzmaktok Grojsh.webp",
    "content/dnd/Strixhaven A Curriculum of Chaos/Player Characters/Borun Erutan Tracker.pdf",
    "z_Assets/Zolon Orielson.pdf",
    "z_Assets/Strixhaven_Improved_Tracker_for_Players.pdf",
    "z_Assets/Borun Erutan.pdf",
    "z_Assets/character-sheet 1.pdf",
    "z_Assets/Roleck Nevari.pdf",
    "z_Assets/Strixhaven Acceptance Packet.pdf",
    "z_Assets/Untitled.canvas"
      "homepage:Open homepage": false
    }
  },
      "homepage:Open homepage": false
    }
  },
  "active": "e7a7b303c61786dc",
  "lastOpenFiles": [
    "ttrpgs/ttrpgs.md",
    "ttrpgs/Non Player Characters/Professor Serafina Onyx.md"
  ]
}